intercom_test/__init__.py
intercom_test/aws_http.py
intercom_test/cases.py
intercom_test/exceptions.py
intercom_test/foreign.py
intercom_test/framework.py
intercom_test/http_best_matches.py
intercom_test/http_stub_server.py
intercom_test/utils.py
intercom_test/version.py
intercom_test/yaml_tools.py
intercom_test/augmentation/__init__.py
intercom_test/augmentation/compact_file.py
intercom_test/augmentation/origin_mapping_stream.py
intercom_test/augmentation/update_file.py
intercom_test/json_asn1/__init__.py
intercom_test/json_asn1/convert.py
intercom_test/json_asn1/types.py
intercom_test-2.3.0.dist-info/LICENSE
intercom_test-2.3.0.dist-info/METADATA
intercom_test-2.3.0.dist-info/WHEEL
intercom_test-2.3.0.dist-info/entry_points.txt
intercom_test-2.3.0.dist-info/top_level.txt
intercom_test-2.3.0.dist-info/RECORD
