Metadata-Version: 2.1
Name: intercom-test
Version: 2.3.0
Summary: Inter-component testing support code for "Interface By Example"
Home-page: https://github.com/PayTrace/intercom_test
Author: Richard T. Weeks
Author-email: rtweeks21@gmail.com
License: Apache License 2.0
Platform: UNKNOWN
Classifier: Programming Language :: Python :: 3 :: Only
Classifier: License :: OSI Approved :: Apache Software License
Classifier: Operating System :: OS Independent
Classifier: Intended Audience :: Developers
Classifier: Intended Audience :: Information Technology
Classifier: Intended Audience :: Other Audience
Classifier: Topic :: Software Development :: Testing
Requires-Dist: PyYAML (<6,>=3.11)
Requires-Dist: packaging (<21,>=20.8)
Requires-Dist: pyasn1 (<1,>=0.4.2)
Requires-Dist: python-Levenshtein (<1,>=0.12)
Provides-Extra: cli
Requires-Dist: docopt-subcommands (<4,>=3.0) ; extra == 'cli'
Requires-Dist: pick (<1,>=0.6.4) ; extra == 'cli'
